LICENSE
README.md
setup.py
skipatom/__init__.py
skipatom/atom_vectors.py
skipatom/create_cooccurrence_pairs.py
skipatom/create_skipatom_embeddings.py
skipatom/create_skipatom_training_data.py
skipatom/elemnet_network.py
skipatom/elemnet_network_classfn.py
skipatom/elpasolite_network.py
skipatom/induced.py
skipatom/model.py
skipatom/one_hot.py
skipatom/random_vectors.py
skipatom/trainer.py
skipatom/training_data.py
skipatom/util.py
skipatom.egg-info/PKG-INFO
skipatom.egg-info/SOURCES.txt
skipatom.egg-info/dependency_links.txt
skipatom.egg-info/entry_points.txt
skipatom.egg-info/requires.txt
skipatom.egg-info/top_level.txt