Metadata-Version: 2.1
Name: skipatom
Version: 1.2.1
Summary: SkipAtom, Distributed representations of atoms, inspired by the Skip-gram model.
Home-page: http://github.com/lantunes/skipatom
Author: Luis M. Antunes
Author-email: lantunes@gmail.com
License: GNU General Public License v3
Keywords: machine learning,materials science,materials informatics,distributed representations,chemistry
Platform: UNKNOWN
Classifier: Development Status :: 5 - Production/Stable
Classifier: Intended Audience :: Developers
Classifier: Topic :: Scientific/Engineering :: Artificial Intelligence
Classifier: License :: OSI Approved :: GNU General Public License v3 (GPLv3)
Classifier: Programming Language :: Python :: 3.6
Requires-Python: >=3.6
Provides-Extra: training
License-File: LICENSE
